{
  "1": {
    "price": 19
  },
  "2": {
    "price": 20
  },
  "3": {
    "price": 21
  },
  "4": {
    "price": 21
  },
  "5": {
    "price": 21
  },
  "6": {
    "price": 21
  },
  "7": {
    "price": 21
  },
  "8": {
    "price": 21
  },
  "9": {
    "price": 21
  },
  "10": {
    "price": 21
  },
  "11": {
    "price": 21
  },
  "12": {
    "price": 20
  },
  "13": {
    "price": 20
  },
  "14": {
    "price": 20
  },
  "15": {
    "price": 20
  },
  "16": {
    "price": 20
  },
  "17": {
    "price": 20
  }
}
